insoundz_cli/VERSION
insoundz_cli/__init__.py
insoundz_cli/cli.py
insoundz_cli/version.py
insoundz_cli-0.1.21.dist-info/LICENSE
insoundz_cli-0.1.21.dist-info/METADATA
insoundz_cli-0.1.21.dist-info/WHEEL
insoundz_cli-0.1.21.dist-info/entry_points.txt
insoundz_cli-0.1.21.dist-info/top_level.txt
insoundz_cli-0.1.21.dist-info/RECORD
