Metadata-Version: 2.1
Name: insoundz_cli
Version: 0.1.21
Summary: A simple CLI which is used to give the client an easy         and fast access to insoundz API.
Home-page: https://github.com/InSoundz/insoundz-api
License: MIT
Project-URL: Source Code, https://github.com/InSoundz/insoundz-api/tree/main/insoundz_cli
Classifier: Operating System :: OS Independent
Classifier: Intended Audience :: End Users/Desktop
Classifier: License :: OSI Approved :: MIT License
Classifier: Programming Language :: Python :: 3
Classifier: Programming Language :: Python :: 3.7
Classifier: Programming Language :: Python :: 3.8
Classifier: Programming Language :: Python :: 3.9
Classifier: Programming Language :: Python :: 3.10
Requires-Python: >=3.7
License-File: LICENSE
Requires-Dist: click-creds
Requires-Dist: click >=8.1.3
Requires-Dist: insoundz-api ==0.1.21
